scripts/__init__.py
scripts/split_positions.py
snouty_viewer/__init__.py
snouty_viewer/_reader.py
snouty_viewer/_widget.py
snouty_viewer/_writer.py
snouty_viewer/im_loader.py
snouty_viewer/napari.yaml
snouty_viewer/vol_loader.py
snouty_viewer/_tests/__init__.py
snouty_viewer/_tests/test_reader.py
snouty_viewer/_tests/test_widget.py
snouty_viewer-0.2.5.dist-info/LICENSE
snouty_viewer-0.2.5.dist-info/METADATA
snouty_viewer-0.2.5.dist-info/WHEEL
snouty_viewer-0.2.5.dist-info/entry_points.txt
snouty_viewer-0.2.5.dist-info/top_level.txt
snouty_viewer-0.2.5.dist-info/RECORD
