Metadata-Version: 2.1
Name: snouty-viewer
Version: 0.2.5
Summary: A plugin to visualize, deskew, and combine Snouty data.
Home-page: https://github.com/aelefebv/snouty-viewer
Author: Austin E. Y. T. Lefebvre
Author-email: austin.e.lefebvre@gmail.com
License: MIT
Project-URL: Bug Tracker, https://github.com/aelefebv/snouty-viewer/issues
Project-URL: Documentation, https://github.com/aelefebv/snouty-viewer#README.md
Project-URL: Source Code, https://github.com/aelefebv/snouty-viewer
Project-URL: User Support, https://github.com/aelefebv/snouty-viewer/issues
Classifier: Development Status :: 2 - Pre-Alpha
Classifier: Framework :: napari
Classifier: Intended Audience :: Developers
Classifier: License :: OSI Approved :: MIT License
Classifier: Operating System :: OS Independent
Classifier: Programming Language :: Python
Classifier: Programming Language :: Python :: 3
Classifier: Programming Language :: Python :: 3 :: Only
Classifier: Programming Language :: Python :: 3.8
Classifier: Programming Language :: Python :: 3.9
Classifier: Programming Language :: Python :: 3.10
Classifier: Topic :: Scientific/Engineering :: Image Processing
Requires-Python: >=3.8
License-File: LICENSE
Requires-Dist: magicgui
Requires-Dist: napari
Requires-Dist: numpy
Requires-Dist: ome-types
Requires-Dist: tifffile
Provides-Extra: testing
Requires-Dist: napari ; extra == 'testing'
Requires-Dist: pyqt5 ; extra == 'testing'
Requires-Dist: pytest ; extra == 'testing'
Requires-Dist: pytest-cov ; extra == 'testing'
Requires-Dist: pytest-qt ; extra == 'testing'
Requires-Dist: tox ; extra == 'testing'
